Metadata-Version: 1.0
Name: basilica
Version: 0.2.8
Summary: Client bindings for basilica.ai embeddings.
Home-page: http://basilica.ai
Author: Michael Lucy
Author-email: mlucy@basilica.ai
License: MIT
Platform: UNKNOWN
